LumoPackage/RandomCube.py
LumoPackage/__init__.py
LumoPackage-2.2022.10.13.dist-info/LICENSE
LumoPackage-2.2022.10.13.dist-info/METADATA
LumoPackage-2.2022.10.13.dist-info/WHEEL
LumoPackage-2.2022.10.13.dist-info/top_level.txt
LumoPackage-2.2022.10.13.dist-info/RECORD
