Metadata-Version: 2.1
Name: LumoPackage
Version: 2.2022.10.13
Summary: Lumo example package
Home-page: UNKNOWN
Author: Lumo group
Author-email: LuMatch@checkmarx.onmicrosoft.com
License: UNKNOWN
Platform: UNKNOWN
Classifier: Programming Language :: Python :: 3
Classifier: License :: OSI Approved :: MIT License
Classifier: Operating System :: OS Independent
Requires-Python: >=3.6
